{"openapi":"3.0.0","paths":{"/auth/register":{"post":{"operationId":"register","parameters":[],"requestBody":{"required":true,"content":{"application/json":{"schema":{"$ref":"#/components/schemas/CreateUserDto"}}}},"responses":{"201":{"description":""}}}},"/auth/login":{"post":{"operationId":"login","parameters":[],"responses":{"201":{"description":""}}}},"/profile":{"get":{"operationId":"getProfile","parameters":[],"responses":{"200":{"description":""}}}}},"info":{"title":"Auth","description":"Auth API description","version":"1.0","contact":{}},"tags":[{"name":"auth","description":""}],"servers":[],"components":{"schemas":{"CreateUserDto":{"type":"object","properties":{"username":{"type":"string"},"password":{"type":"string"}},"required":["username","password"]}}}}